audioset_download/Downloader.py
audioset_download/__init__.py
audioset_download-1.1.dist-info/METADATA
audioset_download-1.1.dist-info/WHEEL
audioset_download-1.1.dist-info/top_level.txt
audioset_download-1.1.dist-info/RECORD
