Metadata-Version: 2.4
Name: audioset-download
Version: 1.1
Summary: This package aims at simplifying the download of the AudioSet dataset.
Home-page: https://github.com/MorenoLaQuatra/audioset-download
Author: Moreno La Quatra
Author-email: moreno.laquatra@gmail.com
Classifier: Programming Language :: Python :: 3
Classifier: Programming Language :: Python :: 3.7
Classifier: Programming Language :: Python :: 3.8
Classifier: Programming Language :: Python :: 3.9
Classifier: License :: OSI Approved :: GNU General Public License v3 (GPLv3)
Classifier: Operating System :: OS Independent
Requires-Python: >=3.7
Requires-Dist: joblib
Requires-Dist: pandas
Requires-Dist: yt-dlp
Provides-Extra: dev
Requires-Dist: pytest>=3.7; extra == "dev"
Dynamic: author
Dynamic: author-email
Dynamic: classifier
Dynamic: description
Dynamic: description-content-type
Dynamic: home-page
Dynamic: provides-extra
Dynamic: requires-dist
Dynamic: requires-python
Dynamic: summary
